canvas_sak/__init__.py
canvas_sak/__main__.py
canvas_sak/canvas_sak.py
canvas_sak/core.py
canvas_sak/md2fhtml.py
canvas_sak/commands/__init__.py
canvas_sak/commands/archive_inbox.py
canvas_sak/commands/code_similarity.py
canvas_sak/commands/collect_reference_info.py
canvas_sak/commands/derive_assignment_score.py
canvas_sak/commands/download_canvas_course.py
canvas_sak/commands/download_submissions.py
canvas_sak/commands/export_letter_grade.py
canvas_sak/commands/grade_discussion.py
canvas_sak/commands/help_me_setup.py
canvas_sak/commands/list_courses.py
canvas_sak/commands/list_due_dates.py
canvas_sak/commands/list_students.py
canvas_sak/commands/message_students.py
canvas_sak/commands/min_grade_analyzer.py
canvas_sak/commands/quiz.py
canvas_sak/commands/rubrics.py
canvas_sak/commands/set_course_image.py
canvas_sak/commands/set_due_dates.py
canvas_sak/commands/set_fudge_points.py
canvas_sak/commands/set_letter_grade.py
canvas_sak/commands/update_assignment.py
canvas_sak/commands/update_assignment_groups.py
canvas_sak/commands/update_quiz.py
canvas_sak/commands/upload_assignment_grades.py
canvas_sak/commands/upload_canvas_course.py
canvas_sak/commands/upload_qti_quiz.py
canvas_sak-1.0.15.dist-info/licenses/LICENSE
canvas_sak-1.0.15.dist-info/METADATA
canvas_sak-1.0.15.dist-info/WHEEL
canvas_sak-1.0.15.dist-info/entry_points.txt
canvas_sak-1.0.15.dist-info/top_level.txt
canvas_sak-1.0.15.dist-info/RECORD
