Metadata-Version: 2.4
Name: canvas-sak
Version: 1.0.15
Summary: Command‑line Swiss Army Knife for Canvas LMS
Requires-Python: >=3.7
License-File: LICENSE
Requires-Dist: arrow==1.2.3
Requires-Dist: beautifulsoup4==4.12.2
Requires-Dist: canvasapi
Requires-Dist: certifi==2023.7.22
Requires-Dist: charset-normalizer==3.2.0
Requires-Dist: click==8.1.3
Requires-Dist: colorama==0.4.6
Requires-Dist: idna==3.4
Requires-Dist: lxml==4.9.3
Requires-Dist: Markdown==3.4.4
Requires-Dist: markdownify==0.11.6
Requires-Dist: mosspy==1.0.9
Requires-Dist: python-dateutil==2.8.2
Requires-Dist: pytz==2023.3
Requires-Dist: requests==2.28.2
Requires-Dist: six==1.16.0
Requires-Dist: soupsieve==2.4.1
Requires-Dist: urllib3==1.26.16
Dynamic: license-file
